[
  {
    "name":"Barot Bellingham",
    "title":"Software Engineer",
    "location":"Austin, TX",
    "email":"Barot@headspring.com",
    "phone":"714232323"
  },
  {
    "name":"Jonathan G",
    "title":"Software Engineer",
    "location":"Austin, TX",
    "email":"Jonathan@headspring.com",
    "phone":"714232323"
  },
  {
    "name":"Hillary Hewitt",
    "title":"Software Engineer",
    "location":"Austin, TX",
    "email":"Hillary@headspring.com",
    "phone":"714232323"
  },
  {
    "name":"Hassum Harrod",
    "title":"Software Engineer",
    "location":"Austin, TX",
    "email":"Hassum@headspring.com",
    "phone":"714232323"
  },
  {
    "name":"Jennifer Jerome",
    "title":"Software Engineer",
    "location":"Austin, TX",
    "email":"Jennifer@headspring.com",
    "phone":"714232323"
  },
  {
    "name":"LaVonne L. LaRue",
    "title":"Software Engineer",
    "location":"Austin, TX",
    "email":"LaVonne@headspring.com",
    "phone":"714232323"
  }
]